workerio/__init__.py
workerio/__version__.py
workerio/exceptions.py
workerio/manager.py
workerio/worker.py
workerio/workers/__init__.py
workerio/workers/partialworker.py
workerio-0.1.0.dist-info/licenses/LICENSE
workerio-0.1.0.dist-info/WHEEL
workerio-0.1.0.dist-info/METADATA
workerio-0.1.0.dist-info/RECORD
