Metadata-Version: 2.4
Name: workerio
Version: 0.1.0
Summary: WorkerIO
Author: aqur1n
Requires-Python: >=3.9
License-Expression: MIT
Classifier: Development Status :: 3 - Alpha
Classifier: Intended Audience :: Developers
Classifier: Topic :: Software Development :: Libraries
Classifier: Programming Language :: Python :: 3
License-File: LICENSE
Project-URL: Homepage, https://github.com/aqur1n/WorkerIO
Project-URL: Issues, https://github.com/aqur1n/WorkerIO/issues
